sbx/__init__.py
sbx/cli.py
sbx/hello.py
nsk_pkg_sbx-0.1.1.dist-info/LICENSE
nsk_pkg_sbx-0.1.1.dist-info/METADATA
nsk_pkg_sbx-0.1.1.dist-info/WHEEL
nsk_pkg_sbx-0.1.1.dist-info/entry_points.txt
nsk_pkg_sbx-0.1.1.dist-info/RECORD
