Metadata-Version: 2.1
Name: nsk-pkg-sbx
Version: 0.1.1
Summary: Packaging POC
License: Apache 2.0
Author: Erik Nelson
Author-email: erik@nsk.io
Requires-Python: >=3.10,<4.0
Classifier: License :: Other/Proprietary License
Classifier: Programming Language :: Python :: 3
Classifier: Programming Language :: Python :: 3.10
Classifier: Programming Language :: Python :: 3.11
Requires-Dist: click (>=8.1.3,<9.0.0)
Requires-Dist: docker (>=6.0.1,<7.0.0)
Requires-Dist: loguru (>=0.7.0,<0.8.0)
